rdf_linkchecker/__init__.py
rdf_linkchecker/__main__.py
rdf_linkchecker/checkers/__init__.py
rdf_linkchecker/checkers/requests_based.py
rdf_linkchecker/example.py
rdf_linkchecker/graph.py
rdf_linkchecker-3.2.0.dist-info/entry_points.txt
rdf_linkchecker-3.2.0.dist-info/LICENSE
rdf_linkchecker-3.2.0.dist-info/WHEEL
rdf_linkchecker-3.2.0.dist-info/METADATA
rdf_linkchecker-3.2.0.dist-info/RECORD
