Metadata-Version: 2.1
Name: rdf-linkchecker
Version: 3.2.0
Summary: `rdf-linkchecker` checks URL in RDF files for reachability
Home-page: https://github.com/WWU-AMM/rdf_linkchecker
License: BSD-3
Author: WWU-AMM
Author-email: rene.fritze@wwu.de
Requires-Python: >=3.8,<4.0
Classifier: Development Status :: 3 - Alpha
Classifier: Intended Audience :: Developers
Classifier: License :: OSI Approved :: BSD License
Classifier: License :: Other/Proprietary License
Classifier: Operating System :: OS Independent
Classifier: Programming Language :: Python :: 3
Classifier: Programming Language :: Python :: 3.10
Classifier: Programming Language :: Python :: 3.7
Classifier: Programming Language :: Python :: 3.8
Classifier: Programming Language :: Python :: 3.9
Classifier: Topic :: Software Development :: Libraries :: Python Modules
Requires-Dist: Brotli (>=1.0.9,<2.0.0)
Requires-Dist: aiohttp (>=3.8.1,<4.0.0)
Requires-Dist: click (>=8.0,<8.2)
Requires-Dist: importlib_metadata (>=4.5.0,<5.0.0); python_version < "3.8"
Requires-Dist: rdflib (>=6.1.1,<7.0.0)
Requires-Dist: rich (>=11,<13)
Requires-Dist: typer[all] (>=0.4.0,<0.5.0)
Requires-Dist: user-agent (>=0.1.10,<0.2.0)
Requires-Dist: validators (>=0.19.0,<0.20.0)
Project-URL: Repository, https://github.com/WWU-AMM/rdf_linkchecker
